README.md
setup.py
yzh_py/__init__.py
yzh_py/config.py
yzh_py/message.py
yzh_py/utils.py
yzh_py.egg-info/PKG-INFO
yzh_py.egg-info/SOURCES.txt
yzh_py.egg-info/dependency_links.txt
yzh_py.egg-info/requires.txt
yzh_py.egg-info/top_level.txt
yzh_py/client/__init__.py
yzh_py/client/base.py
yzh_py/client/api/__init__.py
yzh_py/client/api/apiusersign_client.py
yzh_py/client/api/authentication_client.py
yzh_py/client/api/dataservice_client.py
yzh_py/client/api/h5usersign_client.py
yzh_py/client/api/invoice_client.py
yzh_py/client/api/payment_client.py
yzh_py/client/api/tax_client.py
yzh_py/client/api/model/__init__.py
yzh_py/client/api/model/apiusersign.py
yzh_py/client/api/model/authentication.py
yzh_py/client/api/model/dataservice.py
yzh_py/client/api/model/h5usersign.py
yzh_py/client/api/model/invoice.py
yzh_py/client/api/model/payment.py
yzh_py/client/api/model/tax.py