Metadata-Version: 2.1
Name: yzh-py
Version: 1.0.0
Summary: yunzhanghu service Python client SDK
Home-page: UNKNOWN
Author: yunzhanghu
License: UNKNOWN
Platform: UNKNOWN
Classifier: Programming Language :: Python :: 3
